funccomb/__init__.py
funccomb/core/__init__.py
funccomb/tests/__init__.py
funccomb/tests/test_1984.py
funccomb-0.1.0.dev0.dist-info/licenses/LICENSE.txt
funccomb-0.1.0.dev0.dist-info/METADATA
funccomb-0.1.0.dev0.dist-info/WHEEL
funccomb-0.1.0.dev0.dist-info/top_level.txt
funccomb-0.1.0.dev0.dist-info/RECORD
